wiztype/__init__.py
wiztype/__main__.py
wiztype/cli.py
wiztype/memory/__init__.py
wiztype/memory/properties.py
wiztype/memory/types.py
wiztype/type_dump.py
wiztype/type_tree.py
wiztype-0.1.11.dist-info/entry_points.txt
wiztype-0.1.11.dist-info/licenses/LICENSE
wiztype-0.1.11.dist-info/METADATA
wiztype-0.1.11.dist-info/WHEEL
wiztype-0.1.11.dist-info/RECORD
