Metadata-Version: 2.4
Name: wiztype
Version: 0.1.11
Summary: A type dumper for wizard101
License: MIT
License-File: LICENSE
Author: StarrFox
Author-email: starrfox6312@gmail.com
Requires-Python: >=3.11,<4.0
Classifier: License :: OSI Approved :: MIT License
Classifier: Programming Language :: Python :: 3
Classifier: Programming Language :: Python :: 3.11
Classifier: Programming Language :: Python :: 3.12
Classifier: Programming Language :: Python :: 3.13
Classifier: Programming Language :: Python :: 3.14
Requires-Dist: click (>=8.2.1,<9.0.0)
Requires-Dist: iced-x86 (>=1.21.0,<2.0.0)
Requires-Dist: memobj (>=0.14.1,<0.15.0)
Project-URL: Repository, https://github.com/StarrFox/wiztype
